Nueue/__init__.py
Nueue/queue.py
Nueue-1.0.0.dist-info/LICENSE
Nueue-1.0.0.dist-info/METADATA
Nueue-1.0.0.dist-info/WHEEL
Nueue-1.0.0.dist-info/top_level.txt
Nueue-1.0.0.dist-info/RECORD
