Metadata-Version: 2.1
Name: Nueue
Version: 1.0.0
Summary: An easier way to create the queue.
Home-page: https://github.com/sus2790/Nueue
Author: sus2790
Author-email: sus2790 <amengpan6@gmail.com>
License: MIT License
Project-URL: Home, https://github.com/sus2790/Nueue
Classifier: License :: OSI Approved :: MIT License
License-File: LICENSE
